Ki/__init__.py
Ki/Core/ActivationFunctions.py
Ki/Core/Connection.py
Ki/Core/FeedForwardNetwork.py
Ki/Core/GeneticNetwork.py
Ki/Core/NeuralSwarm.py
Ki/Core/Neuron.py
Ki/Core/__init__.py
Ki-0.2.dist-info/METADATA
Ki-0.2.dist-info/RECORD
Ki-0.2.dist-info/WHEEL
Ki-0.2.dist-info/top_level.txt
